{
  "semantic": {
    "primary": {
      "10": {
        "$type": "color",
        "$value": "#20202d1a"
      },
      "20": {
        "$type": "color",
        "$value": "#20202d33"
      },
      "30": {
        "$type": "color",
        "$value": "#20202d4d"
      },
      "40": {
        "$type": "color",
        "$value": "#20202d66"
      },
      "50": {
        "$type": "color",
        "$value": "#20202d80"
      },
      "60": {
        "$type": "color",
        "$value": "#20202d99"
      },
      "70": {
        "$type": "color",
        "$value": "#20202db3"
      },
      "80": {
        "$type": "color",
        "$value": "#20202dcc"
      },
      "90": {
        "$type": "color",
        "$value": "#20202de6"
      },
      "100": {
        "$type": "color",
        "$value": "{xBase.Color.coldgrey.800}"
      }
    },
    "constant": {
      "10": {
        "$type": "color",
        "$value": "#ffffff1a"
      },
      "20": {
        "$type": "color",
        "$value": "#ffffff33"
      },
      "30": {
        "$type": "color",
        "$value": "#ffffff4d"
      },
      "40": {
        "$type": "color",
        "$value": "#ffffff66"
      },
      "50": {
        "$type": "color",
        "$value": "#ffffff80"
      },
      "60": {
        "$type": "color",
        "$value": "#ffffff99"
      },
      "70": {
        "$type": "color",
        "$value": "#ffffffb3"
      },
      "80": {
        "$type": "color",
        "$value": "#ffffffcc"
      },
      "90": {
        "$type": "color",
        "$value": "#ffffffe6"
      },
      "100": {
        "$type": "color",
        "$value": "{xBase.Color.white.white}"
      }
    },
    "transparent": {
      "0": {
        "$type": "color",
        "$value": "#ffffff00"
      }
    },
    "brand": {
      "10": {
        "$type": "color",
        "$value": "#745ff81a"
      },
      "20": {
        "$type": "color",
        "$value": "#745ff833"
      },
      "30": {
        "$type": "color",
        "$value": "#745ff84d"
      },
      "40": {
        "$type": "color",
        "$value": "#745ff866"
      },
      "50": {
        "$type": "color",
        "$value": "#745ff880"
      },
      "60": {
        "$type": "color",
        "$value": "#745ff899"
      },
      "70": {
        "$type": "color",
        "$value": "#745ff8b3"
      },
      "80": {
        "$type": "color",
        "$value": "#745ff8cc"
      },
      "90": {
        "$type": "color",
        "$value": "#745ff8e6"
      },
      "100": {
        "$type": "color",
        "$value": "{xBase.Color.violet.300}"
      }
    },
    "brand 2": {
      "10": {
        "$type": "color",
        "$value": "#f556701a"
      },
      "20": {
        "$type": "color",
        "$value": "#f5567033"
      },
      "30": {
        "$type": "color",
        "$value": "#f556704d"
      },
      "40": {
        "$type": "color",
        "$value": "#f5567066"
      },
      "50": {
        "$type": "color",
        "$value": "#f5567080"
      },
      "60": {
        "$type": "color",
        "$value": "#f5567099"
      },
      "70": {
        "$type": "color",
        "$value": "#f55670b3"
      },
      "80": {
        "$type": "color",
        "$value": "#f55670cc"
      },
      "90": {
        "$type": "color",
        "$value": "#f55670e6"
      },
      "100": {
        "$type": "color",
        "$value": "{xBase.Color.red.300}"
      }
    },
    "success": {
      "10": {
        "$type": "color",
        "$value": "#34a8531a"
      },
      "20": {
        "$type": "color",
        "$value": "#34a85333"
      },
      "30": {
        "$type": "color",
        "$value": "#34a8534d"
      },
      "40": {
        "$type": "color",
        "$value": "#34a85366"
      },
      "50": {
        "$type": "color",
        "$value": "#34a85380"
      },
      "60": {
        "$type": "color",
        "$value": "#34a85399"
      },
      "70": {
        "$type": "color",
        "$value": "#34a853b3"
      },
      "80": {
        "$type": "color",
        "$value": "#34a853cc"
      },
      "90": {
        "$type": "color",
        "$value": "#34a853e6"
      },
      "100": {
        "$type": "color",
        "$value": "{xBase.Color.green.500}"
      }
    },
    "warning": {
      "10": {
        "$type": "color",
        "$value": "#ff7b001a"
      },
      "20": {
        "$type": "color",
        "$value": "#ff7b0033"
      },
      "30": {
        "$type": "color",
        "$value": "#ff7b004d"
      },
      "40": {
        "$type": "color",
        "$value": "#ff7b0066"
      },
      "50": {
        "$type": "color",
        "$value": "#ff7b0080"
      },
      "60": {
        "$type": "color",
        "$value": "#ff7b0099"
      },
      "70": {
        "$type": "color",
        "$value": "#ff7b00b3"
      },
      "80": {
        "$type": "color",
        "$value": "#ff7b00cc"
      },
      "90": {
        "$type": "color",
        "$value": "#ff7b00e6"
      },
      "100": {
        "$type": "color",
        "$value": "{xBase.Color.orange.400}"
      }
    },
    "error": {
      "10": {
        "$type": "color",
        "$value": "#f53b461a"
      },
      "20": {
        "$type": "color",
        "$value": "#f53b4633"
      },
      "30": {
        "$type": "color",
        "$value": "#f53b464d"
      },
      "40": {
        "$type": "color",
        "$value": "#f53b4666"
      },
      "50": {
        "$type": "color",
        "$value": "#f53b4680"
      },
      "60": {
        "$type": "color",
        "$value": "#f53b4699"
      },
      "70": {
        "$type": "color",
        "$value": "#f53b46b3"
      },
      "80": {
        "$type": "color",
        "$value": "#f53b46cc"
      },
      "90": {
        "$type": "color",
        "$value": "#f53b46e6"
      },
      "100": {
        "$type": "color",
        "$value": "{xBase.Color.red.400}"
      }
    },
    "secondary": {
      "10": {
        "$type": "color",
        "$value": "#7676761a"
      },
      "20": {
        "$type": "color",
        "$value": "#76767633"
      },
      "30": {
        "$type": "color",
        "$value": "#7676764d"
      },
      "40": {
        "$type": "color",
        "$value": "#76767666"
      },
      "50": {
        "$type": "color",
        "$value": "#76767680"
      },
      "60": {
        "$type": "color",
        "$value": "#76767699"
      },
      "70": {
        "$type": "color",
        "$value": "#767676b3"
      },
      "80": {
        "$type": "color",
        "$value": "#767676cc"
      },
      "90": {
        "$type": "color",
        "$value": "#767676e6"
      },
      "100": {
        "$type": "color",
        "$value": "{xBase.Color.grey.500}"
      }
    },
    "neutral 1": {
      "10": {
        "$type": "color",
        "$value": "#f5f5f81a"
      },
      "20": {
        "$type": "color",
        "$value": "#f5f5f833"
      },
      "30": {
        "$type": "color",
        "$value": "#f5f5f84d"
      },
      "40": {
        "$type": "color",
        "$value": "#f5f5f866"
      },
      "50": {
        "$type": "color",
        "$value": "#f5f5f880"
      },
      "60": {
        "$type": "color",
        "$value": "#f5f5f899"
      },
      "70": {
        "$type": "color",
        "$value": "#f5f5f8b3"
      },
      "80": {
        "$type": "color",
        "$value": "#f5f5f8cc"
      },
      "90": {
        "$type": "color",
        "$value": "#f5f5f8e6"
      },
      "100": {
        "$type": "color",
        "$value": "{xBase.Color.coldgrey.0}"
      }
    },
    "brand light": {
      "10": {
        "$type": "color",
        "$value": "#f0f0ff1a"
      },
      "20": {
        "$type": "color",
        "$value": "#f0f0ff33"
      },
      "30": {
        "$type": "color",
        "$value": "#f0f0ff4d"
      },
      "40": {
        "$type": "color",
        "$value": "#f0f0ff66"
      },
      "50": {
        "$type": "color",
        "$value": "#f0f0ff80"
      },
      "60": {
        "$type": "color",
        "$value": "#f0f0ff99"
      },
      "70": {
        "$type": "color",
        "$value": "#f0f0ffb3"
      },
      "80": {
        "$type": "color",
        "$value": "#f0f0ffcc"
      },
      "90": {
        "$type": "color",
        "$value": "#f0f0ffe6"
      },
      "100": {
        "$type": "color",
        "$value": "{xBase.Color.violet.0}"
      }
    },
    "background": {
      "10": {
        "$type": "color",
        "$value": "#ffffff1a"
      },
      "20": {
        "$type": "color",
        "$value": "#ffffff33"
      },
      "30": {
        "$type": "color",
        "$value": "#ffffff4d"
      },
      "40": {
        "$type": "color",
        "$value": "#ffffff66"
      },
      "50": {
        "$type": "color",
        "$value": "#ffffff80"
      },
      "60": {
        "$type": "color",
        "$value": "#ffffff99"
      },
      "70": {
        "$type": "color",
        "$value": "#ffffffb3"
      },
      "80": {
        "$type": "color",
        "$value": "#ffffffcc"
      },
      "90": {
        "$type": "color",
        "$value": "#ffffffe6"
      },
      "100": {
        "$type": "color",
        "$value": "{xBase.Color.white.white}"
      }
    },
    "neutral 2": {
      "10": {
        "$type": "color",
        "$value": "#d8d8e71a"
      },
      "20": {
        "$type": "color",
        "$value": "#d8d8e733"
      },
      "30": {
        "$type": "color",
        "$value": "#d8d8e74d"
      },
      "40": {
        "$type": "color",
        "$value": "#d8d8e766"
      },
      "50": {
        "$type": "color",
        "$value": "#d8d8e780"
      },
      "60": {
        "$type": "color",
        "$value": "#d8d8e799"
      },
      "70": {
        "$type": "color",
        "$value": "#d8d8e7b3"
      },
      "80": {
        "$type": "color",
        "$value": "#d8d8e7cc"
      },
      "90": {
        "$type": "color",
        "$value": "#d8d8e7e6"
      },
      "100": {
        "$type": "color",
        "$value": "{xBase.Color.coldgrey.100}"
      }
    },
    "brand dark": {
      "10": {
        "$type": "color",
        "$value": "#522be11a"
      },
      "20": {
        "$type": "color",
        "$value": "#522be133"
      },
      "30": {
        "$type": "color",
        "$value": "#522be14d"
      },
      "40": {
        "$type": "color",
        "$value": "#522be166"
      },
      "50": {
        "$type": "color",
        "$value": "#522be180"
      },
      "60": {
        "$type": "color",
        "$value": "#522be199"
      },
      "70": {
        "$type": "color",
        "$value": "#522be1b3"
      },
      "80": {
        "$type": "color",
        "$value": "#522be1cc"
      },
      "90": {
        "$type": "color",
        "$value": "#522be1e6"
      },
      "100": {
        "$type": "color",
        "$value": "{xBase.Color.violet.400}"
      }
    },
    "error dark": {
      "10": {
        "$type": "color",
        "$value": "#d90d2d1a"
      },
      "20": {
        "$type": "color",
        "$value": "#d90d2d33"
      },
      "30": {
        "$type": "color",
        "$value": "#d90d2d4d"
      },
      "40": {
        "$type": "color",
        "$value": "#d90d2d66"
      },
      "50": {
        "$type": "color",
        "$value": "#d90d2d80"
      },
      "60": {
        "$type": "color",
        "$value": "#d90d2d99"
      },
      "70": {
        "$type": "color",
        "$value": "#d90d2db3"
      },
      "80": {
        "$type": "color",
        "$value": "#d90d2dcc"
      },
      "90": {
        "$type": "color",
        "$value": "#d90d2de6"
      },
      "100": {
        "$type": "color",
        "$value": "{xBase.Color.red.500}"
      }
    }
  },
  "components": {
    "userchoice": {
      "toggle": {
        "$type": "color",
        "$value": "{semantic.constant.100}"
      },
      "textPrimary": {
        "$type": "color",
        "$value": "{semantic.primary.100}"
      },
      "textLink": {
        "$type": "color",
        "$value": "{semantic.brand.100}"
      },
      "off": {
        "body": {
          "$type": "color",
          "$value": "{semantic.secondary.50}"
        },
        "bodyDisabled": {
          "$type": "color",
          "$value": "{semantic.secondary.20}"
        },
        "border": {
          "$type": "color",
          "$value": "{semantic.brand.100}"
        },
        "borderDisabled": {
          "$type": "color",
          "$value": "{semantic.brand.50}"
        }
      },
      "on": {
        "body": {
          "$type": "color",
          "$value": "{semantic.brand.100}"
        },
        "bodyDisabled": {
          "$type": "color",
          "$value": "{semantic.brand.50}"
        },
        "border": {
          "$type": "color",
          "$value": "{semantic.brand.100}"
        },
        "borderDisabled": {
          "$type": "color",
          "$value": "{semantic.brand.50}"
        }
      },
      "textSecondary": {
        "$type": "color",
        "$value": "{semantic.secondary.100}"
      }
    },
    "divider": {
      "divider": {
        "$type": "color",
        "$value": "{semantic.secondary.40}"
      }
    },
    "counter": {
      "primary": {
        "text": {
          "$type": "color",
          "$value": "{semantic.constant.100}"
        },
        "body": {
          "$type": "color",
          "$value": "{semantic.brand.100}"
        }
      },
      "small": {
        "text": {
          "$type": "color",
          "$value": "{semantic.constant.100}"
        },
        "body": {
          "$type": "color",
          "$value": "{semantic.error.100}"
        }
      },
      "text": {
        "text": {
          "$type": "color",
          "$value": "{semantic.secondary.40}"
        }
      },
      "online": {
        "body": {
          "$type": "color",
          "$value": "{semantic.success.100}"
        }
      }
    },
    "tabbar": {
      "bg": {
        "$type": "color",
        "$value": "{semantic.background.100}"
      },
      "active": {
        "icon": {
          "$type": "color",
          "$value": "{semantic.brand.100}"
        },
        "text": {
          "$type": "color",
          "$value": "{semantic.brand.100}"
        }
      },
      "inactive": {
        "icon": {
          "$type": "color",
          "$value": "{semantic.primary.100}"
        },
        "text": {
          "$type": "color",
          "$value": "{semantic.primary.100}"
        }
      }
    },
    "button": {
      "icon button": {
        "active": {
          "icon": {
            "$type": "color",
            "$value": "{semantic.primary.100}"
          },
          "body": {
            "$type": "color",
            "$value": "{semantic.neutral 1.100}"
          }
        },
        "disabled": {
          "icon": {
            "$type": "color",
            "$value": "{semantic.primary.40}"
          },
          "body": {
            "$type": "color",
            "$value": "{semantic.neutral 1.60}"
          }
        }
      },
      "primary": {
        "default": {
          "icon": {
            "$type": "color",
            "$value": "{semantic.constant.100}"
          },
          "body": {
            "$type": "color",
            "$value": "{semantic.brand.100}"
          },
          "text": {
            "$type": "color",
            "$value": "{semantic.constant.100}"
          }
        },
        "disabled": {
          "text": {
            "$type": "color",
            "$value": "{semantic.constant.60}"
          },
          "icon": {
            "$type": "color",
            "$value": "{semantic.constant.60}"
          },
          "body": {
            "$type": "color",
            "$value": "{semantic.brand.60}"
          }
        },
        "pressed": {
          "text": {
            "$type": "color",
            "$value": "{semantic.constant.100}"
          },
          "icon": {
            "$type": "color",
            "$value": "{semantic.constant.100}"
          },
          "body": {
            "$type": "color",
            "$value": "{semantic.brand dark.100}"
          }
        },
        "loader": {
          "indicator": {
            "$type": "color",
            "$value": "{semantic.constant.100}"
          },
          "body": {
            "$type": "color",
            "$value": "{semantic.constant.20}"
          }
        }
      },
      "warning": {
        "default": {
          "text": {
            "$type": "color",
            "$value": "{semantic.constant.100}"
          },
          "icon": {
            "$type": "color",
            "$value": "{semantic.constant.100}"
          },
          "body": {
            "$type": "color",
            "$value": "{semantic.error.100}"
          }
        },
        "disabled": {
          "text": {
            "$type": "color",
            "$value": "{semantic.constant.60}"
          },
          "icon": {
            "$type": "color",
            "$value": "{semantic.constant.60}"
          },
          "body": {
            "$type": "color",
            "$value": "{semantic.error.60}"
          }
        },
        "pressed": {
          "text": {
            "$type": "color",
            "$value": "{semantic.constant.100}"
          },
          "icon": {
            "$type": "color",
            "$value": "{semantic.constant.100}"
          },
          "body": {
            "$type": "color",
            "$value": "{semantic.error dark.100}"
          }
        },
        "loader": {
          "indicator": {
            "$type": "color",
            "$value": "{semantic.constant.100}"
          },
          "body": {
            "$type": "color",
            "$value": "{semantic.constant.20}"
          }
        }
      },
      "secondary": {
        "default": {
          "text": {
            "$type": "color",
            "$value": "{semantic.primary.100}"
          },
          "icon": {
            "$type": "color",
            "$value": "{semantic.primary.100}"
          },
          "body": {
            "$type": "color",
            "$value": "{semantic.neutral 1.100}"
          }
        },
        "pressed": {
          "text": {
            "$type": "color",
            "$value": "{semantic.primary.100}"
          },
          "icon": {
            "$type": "color",
            "$value": "{semantic.primary.100}"
          },
          "body": {
            "$type": "color",
            "$value": "{semantic.neutral 2.100}"
          }
        },
        "disabled": {
          "text": {
            "$type": "color",
            "$value": "{semantic.primary.40}"
          },
          "icon": {
            "$type": "color",
            "$value": "{semantic.primary.40}"
          },
          "body": {
            "$type": "color",
            "$value": "{semantic.neutral 1.40}"
          }
        },
        "loader": {
          "indicator": {
            "$type": "color",
            "$value": "{semantic.brand dark.100}"
          },
          "body": {
            "$type": "color",
            "$value": "{semantic.brand dark.20}"
          }
        }
      },
      "tretiary": {
        "default": {
          "text": {
            "$type": "color",
            "$value": "{semantic.brand.100}"
          },
          "icon": {
            "$type": "color",
            "$value": "{semantic.brand.100}"
          },
          "body": {
            "$type": "color",
            "$value": "{semantic.transparent.0}"
          }
        },
        "disabled": {
          "text": {
            "$type": "color",
            "$value": "{semantic.brand.60}"
          },
          "icon": {
            "$type": "color",
            "$value": "{semantic.brand.60}"
          },
          "body": {
            "$type": "color",
            "$value": "{semantic.transparent.0}"
          }
        },
        "pressed": {
          "text": {
            "$type": "color",
            "$value": "{semantic.brand dark.100}"
          },
          "icon": {
            "$type": "color",
            "$value": "{semantic.brand dark.100}"
          },
          "body": {
            "$type": "color",
            "$value": "{semantic.transparent.0}"
          }
        }
      },
      "social": {
        "default": {
          "text": {
            "$type": "color",
            "$value": "{semantic.primary.100}"
          },
          "stroke": {
            "$type": "color",
            "$value": "{semantic.neutral 2.100}"
          },
          "body": {
            "$type": "color",
            "$value": "{semantic.transparent.0}"
          }
        },
        "pressed": {
          "text": {
            "$type": "color",
            "$value": "{semantic.primary.100}"
          },
          "stroke": {
            "$type": "color",
            "$value": "{semantic.neutral 2.100}"
          },
          "body": {
            "$type": "color",
            "$value": "{semantic.secondary.10}"
          }
        }
      }
    },
    "navigationbar": {
      "bg": {
        "$type": "color",
        "$value": "{semantic.background.100}"
      },
      "text": {
        "primary": {
          "$type": "color",
          "$value": "{semantic.primary.100}"
        },
        "secondary": {
          "$type": "color",
          "$value": "{semantic.secondary.100}"
        }
      }
    },
    "textfield": {
      "text": {
        "$type": "color",
        "$value": "{semantic.primary.100}"
      },
      "label": {
        "$type": "color",
        "$value": "{semantic.secondary.100}"
      },
      "body": {
        "$type": "color",
        "$value": "{semantic.background.100}"
      },
      "border": {
        "neutral": {
          "$type": "color",
          "$value": "{semantic.neutral 2.100}"
        },
        "focused": {
          "$type": "color",
          "$value": "{semantic.primary.100}"
        },
        "error": {
          "$type": "color",
          "$value": "{semantic.error.100}"
        }
      },
      "icon": {
        "$type": "color",
        "$value": "{semantic.primary.100}"
      },
      "supportingtext": {
        "neutral": {
          "$type": "color",
          "$value": "{semantic.secondary.100}"
        },
        "error": {
          "$type": "color",
          "$value": "{semantic.error.100}"
        },
        "warning": {
          "$type": "color",
          "$value": "{semantic.warning.100}"
        },
        "success": {
          "$type": "color",
          "$value": "{semantic.success.100}"
        }
      }
    },
    "segmentedcontrol": {
      "body": {
        "$type": "color",
        "$value": "{semantic.brand light.100}"
      },
      "active": {
        "body": {
          "$type": "color",
          "$value": "{semantic.brand.80}"
        },
        "text": {
          "$type": "color",
          "$value": "{semantic.constant.100}"
        }
      },
      "inactive": {
        "body": {
          "$type": "color",
          "$value": "{semantic.transparent.0}"
        },
        "text": {
          "$type": "color",
          "$value": "{semantic.secondary.100}"
        }
      }
    },
    "header": {
      "text": {
        "primary": {
          "$type": "color",
          "$value": "{semantic.primary.100}"
        },
        "secodary": {
          "$type": "color",
          "$value": "{semantic.secondary.100}"
        }
      }
    },
    "no image": {
      "icon": {
        "$type": "color",
        "$value": "{semantic.neutral 2.100}"
      }
    },
    "category": {
      "text": {
        "$type": "color",
        "$value": "{semantic.primary.100}"
      },
      "bg": {
        "$type": "color",
        "$value": "{semantic.neutral 1.100}"
      }
    }
  }
}